sqlalchemy_turbodbc/__init__.py
sqlalchemy_turbodbc/connector.py
sqlalchemy_turbodbc/dialect.py
sqlalchemy_turbodbc-1.2.5.dist-info/licenses/AUTHORS
sqlalchemy_turbodbc-1.2.5.dist-info/licenses/LICENSE
sqlalchemy_turbodbc-1.2.5.dist-info/METADATA
sqlalchemy_turbodbc-1.2.5.dist-info/WHEEL
sqlalchemy_turbodbc-1.2.5.dist-info/entry_points.txt
sqlalchemy_turbodbc-1.2.5.dist-info/top_level.txt
sqlalchemy_turbodbc-1.2.5.dist-info/RECORD
