Metadata-Version: 2.4
Name: sqlalchemy_turbodbc
Version: 1.2.5
Summary: SQLAlchemy dialect for Turbodbc
Home-page: https://github.com/dirkjonker/sqlalchemy-turbodbc
Author: Dirk Jonker
Author-email: dirkjonker@gmail.com
License: MIT
Keywords: sql server sqlalchemy turbodbc mssql
Classifier: Development Status :: 5 - Production/Stable
Classifier: Intended Audience :: Developers
Classifier: License :: OSI Approved :: MIT License
Classifier: Programming Language :: Python
Classifier: Topic :: Database
License-File: LICENSE
License-File: AUTHORS
Requires-Dist: sqlalchemy
Requires-Dist: turbodbc>=1.1.0
Dynamic: author
Dynamic: author-email
Dynamic: classifier
Dynamic: description
Dynamic: description-content-type
Dynamic: home-page
Dynamic: keywords
Dynamic: license
Dynamic: license-file
Dynamic: requires-dist
Dynamic: summary
